pypette.py
pypette_web-0.0.2.dist-info/licenses/LICENSE
pypette_web-0.0.2.dist-info/METADATA
pypette_web-0.0.2.dist-info/WHEEL
pypette_web-0.0.2.dist-info/top_level.txt
pypette_web-0.0.2.dist-info/RECORD
